parity-generator/parity_gen.v
// adjust data parity

// Author; Ignas XV

module par_gen (
    input wire [6:0] tt_in,
    input wire p,    // output parity (0-even, 1-odd) 
    output wire [7:0] pdata
);

    reg par; // parity bit

    always @* par = p ? ~^tt_in : ^tt_in; // XOR
    assign pdata = {par, tt_in}; // add parity bit to data
    
endmodule

parity-generator/parity_gen_tb.v
// parity adjustemnet test bench

`timescale 1ns/1ps

module test; 
    reg p;
    reg [6:0] tt_in;
    wire [7:0] pdata;

    par_gen UUT (
        .p(p),
        .tt_in(tt_in),
        .pdata(pdata)
    );

    // test data
    always #2 tt_in = tt_in + 1;
    always #3 p = ~p;

    initial begin
        p = 0;
        tt_in = 0;

        $dumpfile("parity_gen_tb.vcd");
        $dumpvars(0, test);
        $display("\np, tt_in, pdata");
        
        $monitor("%b %b %b", p, tt_in, pdata);
        #20 $finish;
    end 
    
endmodule

parity-generator/parity_gen_tb.vcd
$date
	Wed Mar 19 09:10:13 2025
$end
$version
	Icarus Verilog
$end
$timescale
	1ps
$end
$scope module test $end
$var wire 8 ! pdata [7:0] $end
$var reg 1 " p $end
$var reg 7 # tt_in [6:0] $end
$scope module UUT $end
$var wire 1 " p $end
$var wire 7 $ tt_in [6:0] $end
$var wire 8 % pdata [7:0] $end
$var reg 1 & par $end
$upscope $end
$upscope $end
$enddefinitions $end
$comment Show the parameter values. $end
$dumpall
$end
#0
$dumpvars
0&
b0 %
b0 $
b0 #
0"
b0 !
$end
#2000
1&
b10000001 !
b10000001 %
b1 #
b1 $
#3000
b1 !
b1 %
0&
1"
#4000
b10 !
b10 %
b10 #
b10 $
#6000
b11 !
b11 %
b11 #
b11 $
0"
#8000
1&
b10000100 !
b10000100 %
b100 #
b100 $
#9000
b100 !
b100 %
0&
1"
#10000
1&
b10000101 !
b10000101 %
b101 #
b101 $
#12000
0&
b110 !
b110 %
b110 #
b110 $
0"
#14000
1&
b10000111 !
b10000111 %
b111 #
b111 $
#15000
b111 !
b111 %
0&
1"
#16000
b1000 !
b1000 %
b1000 #
b1000 $
#18000
b1001 !
b1001 %
b1001 #
b1001 $
0"
#20000
b1010 !
b1010 %
b1010 #
b1010 $
